.flake8
.gitignore
.gitmodules
CMakeLists.txt
LICENSE-BSD3
README.md
format.sh
setup.py
.github/workflows/build_and_test.yaml
.github/workflows/check_format.yaml
.github/workflows/check_mpl_requirement.yaml
.github/workflows/release.yaml
cpp/.gitignore
cpp/LICENSE-MPL2
cpp/add_header.sh
cpp/plainmp/bindings/bindings.hpp
cpp/plainmp/bindings/constraint.cpp
cpp/plainmp/bindings/kdtree.cpp
cpp/plainmp/bindings/kinematics.cpp
cpp/plainmp/bindings/ompl_wrapper.cpp
cpp/plainmp/bindings/primitive.cpp
cpp/plainmp/bindings/python.cpp
cpp/plainmp/collision/kdtree.cpp
cpp/plainmp/collision/kdtree.hpp
cpp/plainmp/collision/primitive_sdf.hpp
cpp/plainmp/constraints/composite_constraint.hpp
cpp/plainmp/constraints/primitive.hpp
cpp/plainmp/constraints/primitive_com_in_polytope.cpp
cpp/plainmp/constraints/primitive_com_in_polytope.hpp
cpp/plainmp/constraints/primitive_config_point.cpp
cpp/plainmp/constraints/primitive_config_point.hpp
cpp/plainmp/constraints/primitive_fixed_zaxis.cpp
cpp/plainmp/constraints/primitive_fixed_zaxis.hpp
cpp/plainmp/constraints/primitive_link_pose.cpp
cpp/plainmp/constraints/primitive_link_pose.hpp
cpp/plainmp/constraints/primitive_link_position_bound.cpp
cpp/plainmp/constraints/primitive_link_position_bound.hpp
cpp/plainmp/constraints/primitive_relative_pose.cpp
cpp/plainmp/constraints/primitive_relative_pose.hpp
cpp/plainmp/constraints/primitive_sphere_collision.cpp
cpp/plainmp/constraints/primitive_sphere_collision.hpp
cpp/plainmp/constraints/sequential_constraint.cpp
cpp/plainmp/constraints/sequential_constraint.hpp
cpp/plainmp/kinematics/algorithm.cpp
cpp/plainmp/kinematics/data_structure.hpp
cpp/plainmp/kinematics/kinematics.cpp
cpp/plainmp/kinematics/kinematics.hpp
cpp/plainmp/kinematics/transform.hpp
cpp/plainmp/ompl/.gitignore
cpp/plainmp/ompl/algorithm_selector.cpp
cpp/plainmp/ompl/algorithm_selector.hpp
cpp/plainmp/ompl/custom_goal_samplable_region.cpp
cpp/plainmp/ompl/custom_goal_samplable_region.hpp
cpp/plainmp/ompl/generate_sequence.py
python/plainmp.egg-info/PKG-INFO
python/plainmp.egg-info/SOURCES.txt
python/plainmp.egg-info/dependency_links.txt
python/plainmp.egg-info/requires.txt
python/plainmp.egg-info/top_level.txt
